pytest_env_info.py
pytest_env_info-0.3.0.dist-info/DESCRIPTION.rst
pytest_env_info-0.3.0.dist-info/METADATA
pytest_env_info-0.3.0.dist-info/RECORD
pytest_env_info-0.3.0.dist-info/WHEEL
pytest_env_info-0.3.0.dist-info/entry_points.txt
pytest_env_info-0.3.0.dist-info/metadata.json
pytest_env_info-0.3.0.dist-info/top_level.txt
